README.rst
setup.cfg
setup.py
AdsML/__init__.py
AdsML/bookings.py
AdsML/core.py
AdsML/header.py
AdsML/materials.py
AdsML/order.py
AdsML/parser.py
AdsML/party.py
AdsML/placement.py
AdsML/primitives.py
adsml.egg-info/PKG-INFO
adsml.egg-info/SOURCES.txt
adsml.egg-info/dependency_links.txt
adsml.egg-info/top_level.txt