Metadata-Version: 1.2
Name: adsml
Version: 0.1
Summary: Python implementation of the AdsML spec (www.adsml.biz)
Home-page: https://github.com/bquinn/python-adsml
Author: Brendan Quinn
Author-email: brendan@cluefulmedia.com
License: UNKNOWN
Download-URL: https://github.com/bquinn/python-adsml/archive/0.1.tar.gz
Keywords: api,media,publishing,advertising
Platform: UNKNOWN
Classifier: Development Status :: 3 - Alpha
Classifier: Intended Audience :: Developers
Classifier: License :: OSI Approved :: MIT License
Classifier: Programming Language :: Python :: 3
Requires-Python: >=3
